bgetech_modbus/__init__.py
bgetech_modbus/client.py
bgetech_modbus/exceptions.py
bgetech_modbus/devices/__init__.py
bgetech_modbus/devices/ds100.py
bgetech_modbus-0.1.0b7.dist-info/licenses/LICENSE
bgetech_modbus-0.1.0b7.dist-info/METADATA
bgetech_modbus-0.1.0b7.dist-info/WHEEL
bgetech_modbus-0.1.0b7.dist-info/top_level.txt
bgetech_modbus-0.1.0b7.dist-info/RECORD
