Metadata-Version: 2.4
Name: bgetech-modbus
Version: 0.1.0b7
Summary: Asynchronous Modbus library for B+G e-tech energy meters.
Author-email: Bastian Schroll <info@schroll-it.de>
Maintainer-email: Bastian Schroll <info@schroll-it.de>
License: MIT License
Project-URL: Homepage, https://github.com/Schrolli91/bgetech_modbus/
Project-URL: Issues, https://github.com/Schrolli91/bgetech_modbus/issues
Keywords: modbus,homeassistant,energy,b+g e-tech
Classifier: Programming Language :: Python :: 3
Classifier: Programming Language :: Python :: 3.12
Classifier: Programming Language :: Python :: 3.13
Classifier: Programming Language :: Python :: 3.14
Classifier: License :: OSI Approved :: MIT License
Classifier: Operating System :: OS Independent
Classifier: Intended Audience :: Developers
License-File: LICENSE
Requires-Dist: pymodbus>=3.11.2
Dynamic: license-file
